{
  "thumbnailUrl": "https://img.classistatic.de/api/v1/mo-prod/images/4a/4a7bd584-47e3-45a2-9679-74fcb701aeaa?rule=mo-1024w.jpg",
  "url": "https://suchen.mobile.de/fahrzeuge/details.html?id=412389850",
  "mileage": "74.600 km",
  "location": "Regensburg",
  "country": "DE",
  "year": 2020,
  "title": "Ford Explorer EcoBoost PHEV ST-LINE *7-Sitzer*",
  "description": "",
  "fullDescription": " <ul><li>Elektr. verstellbare Ledersitze mit Memory-Funktion</li> <li>7-Sitzer</li> <li>Klimatisierte Vordersitze</li> <li>Panoramaglasschiebedach</li> <li>PDC hinten &amp; vorne</li> <li>Einpark-Assistent</li> <li>Rückfahrkamera</li> <li>2-Zonen-Klimaautomatik</li> <li>LED-Scheinwerfer</li> <li>20&quot;-Leichtmetallfelgen</li> <li>Sitzheizung vorne &amp; hinten</li> <li>Beheizbare Frontscheibe</li> <li>Beheizbares Multifunktionslederlenkrad</li> <li>Adaptiver Tempomat ACC</li> <li>Warnsystem &quot;Toter Winkel&quot;</li> <li>Dachreling</li> <li>Keyless Entry</li> <li>Elektr. Heckklappe</li> <li>Nebelscheinwerfer</li> <li>Elektr. Fensterheber vorne &amp; hinten</li> <li>Licht- &amp; Regensensor</li> <li>USB-Eingang</li> <li>Uvm.</li></ul>  WIR SIND FORD-VERTRAGSHÄNDLER!! FINANZIERUNG &amp; INZAHLUNGNAHME MÖGLICH!!",
  "price": "43990",
  "currency": "EUR",
  "date": "",
  "id": 412389850,
  "imgUrls": [
    "https://img.classistatic.de/api/v1/mo-prod/images/4a/4a7bd584-47e3-45a2-9679-74fcb701aeaa?rule=mo-1600.jpg",
    "https://img.classistatic.de/api/v1/mo-prod/images/50/50b8bb97-29fc-4ba1-a5ee-a2da4b2cb923?rule=mo-1600.jpg",
    "https://img.classistatic.de/api/v1/mo-prod/images/c1/c118ceca-fbad-4508-8bc6-5ee39227f0ae?rule=mo-1600.jpg",
    "https://img.classistatic.de/api/v1/mo-prod/images/5d/5d1c0fc0-a486-4a7d-9bdb-493825ef66b6?rule=mo-1600.jpg",
    "https://img.classistatic.de/api/v1/mo-prod/images/76/767a511d-0924-4afe-b4dd-5002f6ac27c4?rule=mo-1600.jpg",
    "https://img.classistatic.de/api/v1/mo-prod/images/17/1701bee3-1b59-4c0e-b3aa-b8aa37a8e48f?rule=mo-1600.jpg",
    "https://img.classistatic.de/api/v1/mo-prod/images/99/9981bdfb-861b-49fc-9955-93bfa8228034?rule=mo-1600.jpg",
    "https://img.classistatic.de/api/v1/mo-prod/images/b4/b4659833-0b4c-4a92-a496-adb82b2d3c85?rule=mo-1600.jpg",
    "https://img.classistatic.de/api/v1/mo-prod/images/d8/d83ec2c8-477c-4941-a02f-386c4f14a735?rule=mo-1600.jpg",
    "https://img.classistatic.de/api/v1/mo-prod/images/3f/3f1d1963-f3c5-476f-aeb4-6401ddfb957f?rule=mo-1600.jpg"
  ]
}