{
  "thumbnailUrl": "https://img.classistatic.de/api/v1/mo-prod/images/b6/b61758e1-572f-4f66-b36e-9b472a6754cb?rule=mo-1024w",
  "url": "https://suchen.mobile.de/fahrzeuge/details.html?id=449757329",
  "mileage": "59.970 km",
  "location": "Augsburg",
  "country": "DE",
  "year": 2021,
  "title": "Ford Explorer 3.0 PHEV ST-Line AHK*LED*PANO*ACC*7-SIT",
  "description": "",
  "fullDescription": "Ihr Ansprechpartner für dieses KFZ: <br> <b>Michael Sulinski, Tel: 0821-790869-227</b><br><hr> Ihr Ansprechpartner für dieses KFZ: <br> <b>Noel Büchel, Tel: 082179086919</b><br><hr> Ihr Ansprechpartner für dieses KFZ: <br> <b>Julian Voigt, Tel: 0821 790 869 - 24</b><br><hr> <b>Fahrzeugnummer: MNA16450</b><br><br><b>Ehemalige unverbindliche Preisempfehlung des Automobilherstellers: 81.360 € (ca. -45%)</b><br><hr> <b>Ständig über 800 Fahrzeuge auf Lager! Ford Neuwagen - Tageszulassungen</b><br><br><b>Geprüfte Gebrauchtwagen - 5 Jahre Garantie auf beinahe alle unsere Fahrzeuge - 3x Inspektion inklusive bei nahezu allen Gebrauchtwagen (Big Deal)</b><br><br><b>Finanzierung und Leasing zu Top-Konditionen auch ohne Anzahlung und Ablöse des Vorkredites möglich</b><br><br><b>Beste KFZ-Versicherungskonditionen</b><br><br><b>Inzahlungnahme und Ankauf Ihres Gebrauchten!</b><br><br><b>Wir freuen uns auf Ihren Anruf*<hr> </b>Es handelt sich hier um einen sehr gepflegten Gebrauchtwagen Ford Explorer 3.0 EcoBoost Plug-in-Hybrid ST-Line mit einer TOP AUSSTATTUNG aus 1.-Hand<b><br><ul><li>  </li></b></ul>Deutsches Fahrzeug<b><br>*   </b>Kein Reimport<b><br><ul><li>  </li></b></ul>WIR BIETEN IHNEN WERKSTATT GEPRÜFTE / AUFBEREITETE FAHRZEUGE DIE EINE INTENSIVE QUALITÄTSKONTROLLE DURCHLAUFEN HABEN INKLUSIVE 5 JAHRE GARANTIE AN<b><br><ul><li>  </li></b></ul>Bei Verkauf erhält er TÜV &amp; AU neu und eine grüne Umweltplakette sowie ein vollständiges Pannenset mit Warndreieck Verbandskasten und Warnweste<b><hr> </b>HIGHLIGHTS &amp; PAKETE<b><br>* </b>Sitzausstattung: 7-Sitzer<b><br>* </b>Parkpilotsystem vorn und hinten<b><br>* </b>360 Grad Kamera<b><br>* </b>Totwinkel-Assistent - Cross Traffic Alert und Notbremsfunktion<b><br>* </b>Fahrspur-Pilot<b><br>* </b>Sitzheizung vorn<b><br>* </b>Scheinwerfer-Assistent mit Tag-/Nachtsensor<b><br><ul><li>Knieairbag Fahrerseite</li></ul><br></b>ASSISTENZSYSTEME<b><br>* </b>Panorama-Schiebedach elektr. mit Solar-Reflect<b><br>* </b>Rückfahrkamera mit Split View<b><br>* </b>Adaptive Geschwindigkeits-Regelanlage mit Stop&amp;Go-Funktion<b><br>* </b>Intelligenter Geschwindigkeits-Begrenzer<b><br>* </b>Ausweich-Assistent (Evasive Steer Assistance - ESA)<b><br>* </b>Stauassistent inkl. Stop&amp;Go-Funktion<b><br>* </b>Post-Collision-System<b><br>* </b>Pre-Collision-System<b><br>* </b>Notbrems-Assistent<b><br>* </b>Bordcomputer<b><br>* </b>Zentralverriegelung mit Fernbedienung<b><br>* </b>Sportsitze vorn<b><br>* </b>Parkbremse elektrisch mit Auto-Hold-Funktion<b><br>* </b>Berganfahr-Assistent (Hill-Holder)<b><br>* </b>Bergabfahrassistent<b><br><ul><li>Intelligent Protection System (IPS)</li><li>Anti-Blockier-System (ABS)</li><li>Elektron. Stabilitäts-Programm (ESP)</li><li>Servolenkung elektrisch</li><li>Reifendruck-Kontrollsystem</li></ul><br></b>MOTOR GETRIEBE &amp; FAHRWERK<b><br>* </b>Antriebsart: Allradantrieb<b><br>* </b>Diebstahl-Warnanlage<b><br>* </b>Sport-Fahrwerk<b><br>* </b>KeyFree-System<b><br>* </b>Frontscheibe heizbar<b><br>* </b>Fernlichtassistent (Scheinwerfer mit Abblendautomatik)<b><br>* </b>Power KeyFree-Startfunktion<b><br>* </b>Isofix-Aufnahmen für Kindersitz<b><br><ul><li>Airbag Fahrer-/Beifahrerseite</li><li>Seitenairbag vorn</li><li>Kopfairbag</li><li>Antischlupfregelung (ASR)</li><li>Wegfahrsperre</li></ul><br></b>AUDIO &amp; KOMMUNIKATION<b><br>* </b>Sitzheizung hinten<b><br>* </b>Audio-Navigationssystem Ford mit AppLink<b><br>* </b>Ford SYNC 3 mit Navigation<b><br>* </b>Radioempfang digital (DAB)<b><br>* </b>Farbdisplay (10.1 Zoll)<b><br>* </b>Vorrüstung Mobiltelefon/Handy mit Bluetooth-Schnittstelle<b><br>* </b>Sprachsteuerung<b><br>* </b>Induktionsladeschale für mobile Endgeräte<b><br>* </b>USB-Anschluss<b><br>* </b>FordPass Connect inkl. eCall<b><br><br></b>INTERIEUR<b><br>* </b>Sitze vorn klimatisiert<b><br>* </b>Lenkrad heizbar<b><br>* </b>Lenkrad mit Schaltwippen<b><br>* </b>Carbon-Dekor<b><br>* </b>Lenkrad (Sport/Leder - ST)<b><br>* </b>Sitzbezug/Polsterung Leder Premium<b><br>* </b>Sitz vorn links elektr. verstellbar (10-fach - mit Memory)<b><br>* </b>Lendenwirbelstütze Sitz vorn links - elektr. verstellbar<b><br>* </b>Sitz vorn rechts elektr. verstellbar (8-fach)<b><br>* </b>Lendenwirbelstütze Sitz vorn rechts - elektr. verstellbar<b><br>* </b>Mittelarmlehne vorn mit Staufach<b><br><br></b>LICHT &amp; SICHT<b><br>* </b>Schadstoffarm nach Abgasnorm Euro 6d-TEMP<b><br>* </b>Sound-System Bang &amp; Olufsen Play<b><br>* </b>Scheinwerfer LED<b><br>* </b>Frontkamera mit Split View<b><br>* </b>Audiobedienung am Lenkrad<b><br>* </b>Tagfahrlicht LED<b><br>* </b>Nebelscheinwerfer LED<b><br>* </b>Heckleuchten LED<b><br>* </b>Steckdose 230V<b><br>* </b>Karosserie: 5-türig<b><br><br></b>RÄDER<b><br><ul><li>Reifen-Reparatur-Kit</li></ul><br></b>TECHNIK &amp; SICHERHEIT<b><br><ul><li>Wankneigungskontrolle (Roll Stability Control - RSC)</li><li>Elektr. Bremskraftverteilung</li></ul><br></b>EXTERIEUR<b><br>* </b>Metallic-Lackierung<b><br>* </b>Anhängerkupplung abnehmbar<b><br>* </b>Bodenleuchte im Aussenspiegel<b><br>* </b>Aussenspiegel elektr. anklappbar<b><br>* </b>Aussenspiegel elektr. verstell- und heizbar - mit Memory<b><br>* </b>Wärmeschutzverglasung<b><br>* </b>Verglasung hinten abgedunkelt <br><ul><li>...u.v.m.  <hr> BigDeal: 3x Inspektionen gem. Herstellervorgabe. Sie bezahlen nur das Material und eventuelle Zusatzarbeiten - gültig in allen unseren Filialen.</li></ul>G5: Bis 5 Jahre Händlereigengarantie auf 10 wichtige Baugruppen.<br>Der Erstattungssatz für Lohn und Material richtet sich nach der Gesamtfahrleistung bei Schadenseintritt.<br>Einzelheiten unter <b>www.haendlereigengarantie.eu</b> oder bei uns. <br><hr> Sie möchten ihr neues Fahrzeug finanzieren oder leasen? Kein Problem! Gerne erstellen wir ihnen ein Finanzierungs- oder Leasingangebot mit ihrer Wunschrate. Als Vertragshändler bieten wir Ihnen besten Service und kompetente Beratung zu allen Fragen rund ums Automobil. Irrtum und Zwischenverkauf vorbehalten <br>",
  "price": "44650",
  "currency": "EUR",
  "date": "",
  "id": 449757329,
  "imgUrls": [
    "https://img.classistatic.de/api/v1/mo-prod/images/b6/b61758e1-572f-4f66-b36e-9b472a6754cb?rule=mo-1600",
    "https://img.classistatic.de/api/v1/mo-prod/images/19/1936e6d1-9e11-4a0a-aa44-c2e50fabcd96?rule=mo-1600",
    "https://img.classistatic.de/api/v1/mo-prod/images/ba/baf0004e-97fb-4be5-bfe9-5167e326a188?rule=mo-1600",
    "https://img.classistatic.de/api/v1/mo-prod/images/90/904df25e-ecda-43f1-a43c-5c5d59d5e881?rule=mo-1600",
    "https://img.classistatic.de/api/v1/mo-prod/images/84/84e551a4-dee5-4037-9d98-98726689699a?rule=mo-1600",
    "https://img.classistatic.de/api/v1/mo-prod/images/f0/f049ffb2-7870-4986-9c6c-118e9134736a?rule=mo-1600",
    "https://img.classistatic.de/api/v1/mo-prod/images/95/959fd67f-9839-4f4e-8b76-654aa40a06cc?rule=mo-1600",
    "https://img.classistatic.de/api/v1/mo-prod/images/55/555b9453-f964-4ab6-9f7d-9e4c85ef2d1b?rule=mo-1600",
    "https://img.classistatic.de/api/v1/mo-prod/images/3d/3da228b2-491f-4f88-960a-8c38806a6caf?rule=mo-1600",
    "https://img.classistatic.de/api/v1/mo-prod/images/36/367c4faf-0a39-41c6-b06a-5caeea594d60?rule=mo-1600",
    "https://img.classistatic.de/api/v1/mo-prod/images/58/58dbaa1d-2e7b-4541-854b-e90c71231a0d?rule=mo-1600",
    "https://img.classistatic.de/api/v1/mo-prod/images/61/61558d51-bc2c-43fb-8b6e-564ed7b51620?rule=mo-1600",
    "https://img.classistatic.de/api/v1/mo-prod/images/c2/c2ac6f3e-e6ed-4704-b4f5-c520ba2c9bbe?rule=mo-1600",
    "https://img.classistatic.de/api/v1/mo-prod/images/ae/aeebcebb-5e46-4f51-ac76-8673b64616d0?rule=mo-1600",
    "https://img.classistatic.de/api/v1/mo-prod/images/47/47b8128a-f928-4d2d-a56c-712a7bf3cd44?rule=mo-1600",
    "https://img.classistatic.de/api/v1/mo-prod/images/ad/adff2bf6-6672-4c9d-96c0-f6b758d88643?rule=mo-1600",
    "https://img.classistatic.de/api/v1/mo-prod/images/ea/eabc85b1-683e-4f7e-82c4-51f78d548e39?rule=mo-1600",
    "https://img.classistatic.de/api/v1/mo-prod/images/31/3126c640-aba9-409a-aaaa-26a07c3bf770?rule=mo-1600",
    "https://img.classistatic.de/api/v1/mo-prod/images/e4/e4f46c9f-3486-441f-bb95-f239c385fc51?rule=mo-1600",
    "https://img.classistatic.de/api/v1/mo-prod/images/b9/b95f4cc2-54fb-4840-bd57-bc57a0226695?rule=mo-1600",
    "https://img.classistatic.de/api/v1/mo-prod/images/70/7087f9f1-33da-432a-985e-8e92c7e443e9?rule=mo-1600",
    "https://img.classistatic.de/api/v1/mo-prod/images/cd/cdfa42f8-019e-4526-8b6d-62ce42635d52?rule=mo-1600",
    "https://img.classistatic.de/api/v1/mo-prod/images/05/051df82e-bd81-4cf2-afa0-d35a7efca5b5?rule=mo-1600",
    "https://img.classistatic.de/api/v1/mo-prod/images/1a/1ac96a20-83ff-4753-8900-e3019d42dac0?rule=mo-1600",
    "https://img.classistatic.de/api/v1/mo-prod/images/81/81e5fa66-da6c-4e7e-b574-134bddc428fb?rule=mo-1600",
    "https://img.classistatic.de/api/v1/mo-prod/images/19/193f641e-559e-4c68-9e68-c11f8285150a?rule=mo-1600",
    "https://img.classistatic.de/api/v1/mo-prod/images/c5/c5987f9b-8f53-413b-a897-9e0413789a13?rule=mo-1600",
    "https://img.classistatic.de/api/v1/mo-prod/images/c8/c850836d-f735-4a30-8be0-e12e8f1cb88f?rule=mo-1600",
    "https://img.classistatic.de/api/v1/mo-prod/images/42/42ef77a6-9eb4-4a4d-8bce-2b173e00019a?rule=mo-1600",
    "https://img.classistatic.de/api/v1/mo-prod/images/cc/cc15658e-3056-425e-b0f0-76790da629d9?rule=mo-1600",
    "https://img.classistatic.de/api/v1/mo-prod/images/87/87627d13-6ee7-4eb3-a68a-84797e72f842?rule=mo-1600",
    "https://img.classistatic.de/api/v1/mo-prod/images/9c/9c8e2df2-ec93-4dc2-9979-0861a87137ba?rule=mo-1600"
  ]
}