{
  "thumbnailUrl": "https://img.classistatic.de/api/v1/mo-prod/images/a6/a65cd755-a29e-40f9-9586-521af21d3052?rule=mo-1024w",
  "url": "https://suchen.mobile.de/fahrzeuge/details.html?id=437321072",
  "mileage": "58.200 km",
  "location": "Leipzig",
  "country": "DE",
  "year": 2021,
  "title": "Ford Explorer 3.0 EcoBoost Plug-in-Hybrid 4x4 Autom. ",
  "description": "",
  "fullDescription": "<br><b>Highlights</b><br><br><ul><li>Adaptive Geschwindigkeitsregelanlage (ASCC) mit Abstandsregelung und Stopp-Funktion (0-180 km/h)</li><li>Panorama-Schiebedach, elektrisch </li><li>Sportfahrwerk </li></ul><br><b>Ausstattungspakete</b><br><br><ul><li>Getriebe Automatik - Typ: 10R80 (10-Stufen)</li><li>Sportpaket </li></ul><br><b>Assistenzsysteme</b><br><br><ul><li>aktiver Park-Assistent Plus, Ein- und Auspark-Funktion und teilautomatisierter Fahrzeugführung</li><li>Berganfahr- und Bergabfahrassistent </li><li>Berganfahrassistent</li><li>Fahrassistenz-System: Fahrspur-Pilot</li><li>Fahrassistenz-System: Post-Collision-System</li><li>Fahrassistenz-System: Pre-Collision-System</li><li>Geschwindigkeitsbegrenzer </li><li>Regensensor</li><li>Stauassistenten</li><li>Verkehrszeichenerkennung </li></ul><br><b>Multimedia &amp; Kommunikation</b><br><br><ul><li>Audio-Navigationssystem Ford mit AppLink </li><li>Bang &amp; Olufsen</li><li>Digitaler Radioempfang (DAB)</li><li>Farbdisplay (10,1 Zoll)</li><li>Ford SYNC mit Navigation</li><li>Induktionsladeschale für Smartphone </li><li>Subwoofer </li></ul><br><b>Sicherheit</b><br><br><ul><li>Allradantrieb</li><li>Ausweichassistent </li><li>Auto-Hold-Funktion </li><li>Diebstahl-Alarmanlage</li><li>Elektronisches Stabilitätsprogramm (ESP) </li><li>Frontscheibe beheizbar </li><li>Innenspiegel automatisch abblendend </li><li>ISOFIX-Kindersitzbefestigung hinten auf den äußeren Sitzplätzen inkl. Top-Tether-Verankerungspunkten</li><li>Knieairbag Beifahrerseite</li><li>ParkPilot im Front- und Heckbereich </li><li>Reifendruck-Kontrollsystem</li><li>Reserverad </li><li>Rückfahrkamera </li><li>Seiten- und Kopfairbags </li><li>Spurhalteassistent </li><li>Totwinkelassistent </li><li>Wankneigungskontrolle (Roll Stability Control, RSC)</li><li>Zentralverriegelung mit schlüsselintegrierter Funkfernbedienung</li></ul><br><b>Interieur</b><br><br><ul><li>230-V-Steckdose </li><li>7 Sitze </li><li>Digitale Instrumentierung 12,3&quot;-Display</li><li>Einstiegschienen mit Modell-Schriftzug</li><li>Fensterheber elektr. vorne und hinten</li><li>Innenausstattung: Carbon-Dekor</li><li>Klimaautomatik 2-Zonen</li><li>Lendenwirbelstütze</li><li>Lenkrad mit Schaltwippen </li><li>Mittelarmlehne</li><li>Sitz vorn rechts elektr. verstellbar (8-fach)</li><li>Sitzbelüftung vorn </li><li>Sitzbezug / Polsterung: Leder Premium</li><li>Sitzheizung hinten </li><li>Sportsitze vorn </li></ul><br><b>Exterieur</b><br><br><ul><li>Außenspiegel elektr. anklappbar</li><li>Außenspiegel elektr. einstell- und beheizbar</li><li>Dachreling, schwarz </li><li>Heckspoiler Wagenfarbe</li><li>Kofferraumdeckel / Heckklappe elektr. betätigt (Öffnung, sensorgesteuert)</li></ul><br><b>Licht &amp; Sicht</b><br><br><ul><li>LED-Scheinwerfer</li><li>LED-Tagfahrlicht</li><li>Lichtsensor</li><li>Nebelscheinwerfer</li><li>Privacy Verglasung im Fond</li></ul><br><b>Sonstiges</b><br><br><ul><li>Fahrersitz elektrisch einstellbar</li><li>Fahrersitz mit Memory-Funktion</li><li>Fernlichtassistent</li><li>Lederlenkrad mit Multifunktion, beheizbar</li><li>Sicherheitspaket</li><li>Start-Stopp-System</li><li>Vorbereitung für Anhängevorrichtung </li><li>HU+AU neu</li><li>Metallic-Lackierung</li><li>Nichtraucherfahrzeug</li><li>Scheckheft gepflegt</li></ul>",
  "price": "43990",
  "currency": "EUR",
  "date": "",
  "id": 437321072,
  "imgUrls": [
    "https://img.classistatic.de/api/v1/mo-prod/images/a6/a65cd755-a29e-40f9-9586-521af21d3052?rule=mo-1600"
  ]
}