{
  "thumbnailUrl": "https://img.classistatic.de/api/v1/mo-prod/images/6a/6a034249-bd6b-4397-8130-2c1e77608fe9?rule=mo-1024w",
  "url": "https://suchen.mobile.de/fahrzeuge/details.html?id=433197819",
  "mileage": "26.420 km",
  "location": "Augsburg",
  "country": "DE",
  "year": 2021,
  "title": "Ford Explorer Plug-in-Hybrid ST-Line LED*PANO*7-SITZE",
  "description": "",
  "fullDescription": "Ihr Ansprechpartner für dieses KFZ: <br> <b>Michael Sulinski, Tel: 0821-790869-227</b><br><hr> Ihr Ansprechpartner für dieses KFZ: <br> <b>Noel Büchel, Tel: 082179086919</b><br><hr> Ihr Ansprechpartner für dieses KFZ: <br> <b>Julian Voigt, Tel: 0821 790 869 - 24</b><br><hr> <b>Fahrzeugnummer: GC84294</b><br><hr> <b>Ständig über 800 Fahrzeuge auf Lager! Ford Neuwagen - Tageszulassungen</b><br><br><b>Geprüfte Gebrauchtwagen - 5 Jahre Garantie auf beinahe alle unsere Fahrzeuge - 3x Inspektion inklusive bei nahezu allen Gebrauchtwagen (Big Deal)</b><br><br><b>Finanzierung und Leasing zu Top-Konditionen auch ohne Anzahlung und Ablöse des Vorkredites möglich</b><br><br><b>Beste KFZ-Versicherungskonditionen</b><br><br><b>Inzahlungnahme und Ankauf Ihres Gebrauchten!</b><br><br><b>Wir freuen uns auf Ihren Anruf</b><hr> <b>Es handelt sich hier um einen sehr gepflegten Gebrauchtwagen Ford Explorer 3.0 EcoBoost Plug-in-Hybrid ST-Line mit einer TOP AUSSTATTUNG aus 1.-Hand</b><br><br><b> Deutsches Fahrzeug</b><br><ul><li><b>Kein Reimport</b></li></ul><br><b> WIR BIETEN IHNEN WERKSTATT GEPRÜFTE / AUFBEREITETE FAHRZEUGE DIE EINE INTENSIVE QUALITÄTSKONTROLLE DURCHLAUFEN HABEN INKLUSIVE 5 JAHRE GARANTIE AN</b><br><br><b> Bei Verkauf erhält er TÜV &amp; AU neu und eine grüne Umweltplakette sowie ein vollständiges Pannenset mit Warndreieck Verbandskasten und Warnweste</b><hr> <b>HIGHLIGHTS &amp; PAKETE</b><br><ul><li><b>Sitzausstattung: 7-Sitzer</b></li><li><b>Parkpilotsystem vorn und hinten</b></li><li><b>360 Grad Kamera</b></li><li><b>Totwinkel-Assistent - Cross Traffic Alert und Notbremsfunktion</b></li><li><b>Fahrspur-Pilot</b></li><li><b>Sitzheizung vorn</b></li><li><b>Scheinwerfer-Assistent mit Tag-/Nachtsensor</b></li><li>Knieairbag Fahrerseite</li></ul><br><b>ASSISTENZSYSTEME</b><br><ul><li><b>Panorama-Schiebedach elektr. mit Solar-Reflect</b></li><li><b>Rückfahrkamera mit Split View</b></li><li><b>Adaptive Geschwindigkeits-Regelanlage mit Stop&amp;Go-Funktion</b></li><li><b>Intelligenter Geschwindigkeits-Begrenzer</b></li><li><b>Ausweich-Assistent (Evasive Steer Assistance - ESA)</b></li><li><b>Stauassistent inkl. Stop&amp;Go-Funktion</b></li><li><b>Post-Collision-System</b></li><li><b>Pre-Collision-System</b></li><li><b>Notbrems-Assistent</b></li><li><b>Bordcomputer</b></li><li><b>Zentralverriegelung mit Fernbedienung</b></li><li><b>Sportsitze vorn</b></li><li><b>Parkbremse elektrisch mit Auto-Hold-Funktion</b></li><li><b>Berganfahr-Assistent (Hill-Holder)</b></li><li><b>Bergabfahrassistent</b></li><li>Intelligent Protection System (IPS)</li><li>Anti-Blockier-System (ABS)</li><li>Elektron. Stabilitäts-Programm (ESP)</li><li>Servolenkung elektrisch</li><li>Reifendruck-Kontrollsystem</li></ul><br><b>MOTOR GETRIEBE &amp; FAHRWERK</b><br><ul><li><b>Antriebsart: Allradantrieb</b></li><li><b>Diebstahl-Warnanlage</b></li><li><b>Sport-Fahrwerk</b></li><li><b>KeyFree-System</b></li><li><b>Frontscheibe heizbar</b></li><li><b>Fernlichtassistent (Scheinwerfer mit Abblendautomatik)</b></li><li><b>Power KeyFree-Startfunktion</b></li><li><b>Isofix-Aufnahmen für Kindersitz</b></li><li>Airbag Fahrer-/Beifahrerseite</li><li>Seitenairbag vorn</li><li>Kopfairbag</li><li>Antischlupfregelung (ASR)</li><li>Wegfahrsperre</li></ul><br><b>AUDIO &amp; KOMMUNIKATION</b><br><ul><li><b>Sitzheizung hinten</b></li><li><b>Audio-Navigationssystem Ford mit AppLink</b></li><li><b>Ford SYNC 3 mit Navigation</b></li><li><b>Radioempfang digital (DAB)</b></li><li><b>Farbdisplay (10.1 Zoll)</b></li><li><b>Vorrüstung Mobiltelefon/Handy mit Bluetooth-Schnittstelle</b></li><li><b>Sprachsteuerung</b></li><li><b>Induktionsladeschale für mobile Endgeräte</b></li><li><b>USB-Anschluss</b></li><li><b>FordPass Connect inkl. eCall</b></li></ul><br><b>INTERIEUR</b><br><ul><li><b>Sitze vorn klimatisiert</b></li><li><b>Lenkrad heizbar</b></li><li><b>Lenkrad mit Schaltwippen</b></li><li><b>Carbon-Dekor</b></li><li><b>Lenkrad (Sport/Leder - ST)</b></li><li><b>Sitzbezug/Polsterung Leder Premium</b></li><li><b>Sitz vorn links elektr. verstellbar (10-fach - mit Memory)</b></li><li><b>Lendenwirbelstütze Sitz vorn links - elektr. verstellbar</b></li><li><b>Sitz vorn rechts elektr. verstellbar (8-fach)</b></li><li><b>Lendenwirbelstütze Sitz vorn rechts - elektr. verstellbar</b></li><li><b>Mittelarmlehne vorn mit Staufach</b></li></ul><br><b>LICHT &amp; SICHT</b><br><ul><li><b>Schadstoffarm nach Abgasnorm Euro 6d-TEMP</b></li><li><b>Sound-System Bang &amp; Olufsen Play</b></li><li><b>Scheinwerfer LED</b></li><li><b>Frontkamera mit Split View</b></li><li><b>Audiobedienung am Lenkrad</b></li><li><b>Tagfahrlicht LED</b></li><li><b>Nebelscheinwerfer LED</b></li><li><b>Heckleuchten LED</b></li><li><b>Steckdose 230V</b></li><li><b>Karosserie: 5-türig</b></li></ul><br><b>RÄDER</b><br><ul><li>Reifen-Reparatur-Kit</li></ul><br><b>TECHNIK &amp; SICHERHEIT</b><br><ul><li>Wankneigungskontrolle (Roll Stability Control - RSC)</li><li>Elektr. Bremskraftverteilung</li></ul><br><b>EXTERIEUR</b><br><ul><li><b>Metallic-Lackierung</b></li><li><b>Bodenleuchte im Aussenspiegel</b></li><li><b>Aussenspiegel elektr. anklappbar</b></li><li><b>Aussenspiegel elektr. verstell- und heizbar - mit Memory</b></li><li><b>Wärmeschutzverglasung</b></li><li><b>Verglasung hinten abgedunkelt (Privacy Glass)</b></li><li><b>Dachreling schwarz</b></li></ul><br><b>SONSTIGE AUSSTATTUNGEN</b><br><ul><li><b>Klimaautomatik 3-Zonen</b></li><li>**Aktive </li><li>...u.v.m.  <hr> BigDeal: 3x Inspektionen gem. Herstellervorgabe. Sie bezahlen nur das Material und eventuelle Zusatzarbeiten - gültig in allen unseren Filialen.</li></ul>G5: Bis 5 Jahre Händlereigengarantie auf 10 wichtige Baugruppen.<br>Der Erstattungssatz für Lohn und Material richtet sich nach der Gesamtfahrleistung bei Schadenseintritt.<br>Einzelheiten unter <b>www.haendlereigengarantie.eu</b> oder bei uns. <br><hr> Sie möchten ihr neues Fahrzeug finanzieren oder leasen? Kein Problem! Gerne erstellen wir ihnen ein Finanzierungs- oder Leasingangebot mit ihrer Wunschrate. Als Vertragshändler bieten wir Ihnen besten Service und kompetente Beratung zu allen Fragen rund ums Automobil. Irrtum und Zwischenverkauf vorbehalten <br>",
  "price": "47450",
  "currency": "EUR",
  "date": "",
  "id": 433197819,
  "imgUrls": [
    "https://img.classistatic.de/api/v1/mo-prod/images/6a/6a034249-bd6b-4397-8130-2c1e77608fe9?rule=mo-1600",
    "https://img.classistatic.de/api/v1/mo-prod/images/07/0778b116-dc02-438a-9b34-8e773cf29d04?rule=mo-1600",
    "https://img.classistatic.de/api/v1/mo-prod/images/b0/b0943060-04df-4587-a634-3a3ab1bbc593?rule=mo-1600",
    "https://img.classistatic.de/api/v1/mo-prod/images/55/55e7584f-2f8c-4f8e-9dd4-8aa44920e0a1?rule=mo-1600",
    "https://img.classistatic.de/api/v1/mo-prod/images/b4/b433673d-57cc-46d4-9e6c-a100faf9f144?rule=mo-1600",
    "https://img.classistatic.de/api/v1/mo-prod/images/8b/8b240c5f-cc57-4d03-8a2e-6735971243f1?rule=mo-1600",
    "https://img.classistatic.de/api/v1/mo-prod/images/98/98b16de2-2fa3-40a2-b20e-d6708af953d7?rule=mo-1600",
    "https://img.classistatic.de/api/v1/mo-prod/images/ca/caa9c375-76c4-4dc9-979e-ae4b2bc513f5?rule=mo-1600",
    "https://img.classistatic.de/api/v1/mo-prod/images/8d/8d547bb8-bf38-496e-a425-bca4d840a313?rule=mo-1600",
    "https://img.classistatic.de/api/v1/mo-prod/images/b3/b3a8bfca-93d0-442a-86f1-59c117b723fc?rule=mo-1600",
    "https://img.classistatic.de/api/v1/mo-prod/images/aa/aadd4985-246a-42eb-8666-0e708d6cf332?rule=mo-1600",
    "https://img.classistatic.de/api/v1/mo-prod/images/05/050304cc-c1ac-477a-987f-10bc84f9cc35?rule=mo-1600",
    "https://img.classistatic.de/api/v1/mo-prod/images/fa/fae344b2-5321-45b0-959b-a1b111fcf08a?rule=mo-1600",
    "https://img.classistatic.de/api/v1/mo-prod/images/c9/c9a681c1-304e-4cc3-99d7-f08ac0755070?rule=mo-1600",
    "https://img.classistatic.de/api/v1/mo-prod/images/bf/bfb9d65a-e717-4717-a308-0f93e0ac21ed?rule=mo-1600",
    "https://img.classistatic.de/api/v1/mo-prod/images/7b/7b43f6fa-f9f0-4532-b98f-1aabdfd04cdf?rule=mo-1600",
    "https://img.classistatic.de/api/v1/mo-prod/images/d3/d3a2935f-2fe2-40d9-9c53-cfce76447db8?rule=mo-1600",
    "https://img.classistatic.de/api/v1/mo-prod/images/cb/cb8da3f6-acd8-4a88-a1c1-b2a61093adab?rule=mo-1600",
    "https://img.classistatic.de/api/v1/mo-prod/images/32/32b43b38-afab-4f4d-ac16-fbed679d969b?rule=mo-1600",
    "https://img.classistatic.de/api/v1/mo-prod/images/6b/6b3cb1c8-1dfa-4947-b090-8d18c76ea391?rule=mo-1600",
    "https://img.classistatic.de/api/v1/mo-prod/images/a8/a8ea1998-75c3-4b5e-9ae9-f8a885b963fb?rule=mo-1600",
    "https://img.classistatic.de/api/v1/mo-prod/images/6a/6adc1413-3e65-4d60-abcf-721ed380961b?rule=mo-1600",
    "https://img.classistatic.de/api/v1/mo-prod/images/c6/c6574b42-f840-4b84-9793-8eec682c85cf?rule=mo-1600",
    "https://img.classistatic.de/api/v1/mo-prod/images/7a/7a0a8c01-d3dd-476a-bb1f-f6f0075c4f0f?rule=mo-1600",
    "https://img.classistatic.de/api/v1/mo-prod/images/7d/7d9cd571-4789-47d6-8834-e54b2dd95841?rule=mo-1600",
    "https://img.classistatic.de/api/v1/mo-prod/images/3c/3c12557b-1a6f-4af2-98ea-9212cfa3a0bc?rule=mo-1600",
    "https://img.classistatic.de/api/v1/mo-prod/images/6f/6fd28eb6-a4b5-4785-bb9d-cd22a9151fc4?rule=mo-1600",
    "https://img.classistatic.de/api/v1/mo-prod/images/35/35f40e59-4764-4a88-82fa-d584edf436f1?rule=mo-1600",
    "https://img.classistatic.de/api/v1/mo-prod/images/8d/8d9afbd9-c887-44f1-ae18-386a81201989?rule=mo-1600",
    "https://img.classistatic.de/api/v1/mo-prod/images/ce/ce167725-9e5e-47b9-86ce-2c6a9319320f?rule=mo-1600"
  ]
}