{
  "thumbnailUrl": "https://img.classistatic.de/api/v1/mo-prod/images/22/22ee4195-1b64-47be-81c0-0b62c19193b1?rule=mo-1024w",
  "url": "https://suchen.mobile.de/fahrzeuge/details.html?id=429251699",
  "mileage": "57.193 km",
  "location": "Mönchhagen",
  "country": "DE",
  "year": 2021,
  "title": "Ford Explorer ST-Line Plug-in-Hybrid 4x4 7 Sitzer AHK",
  "description": "",
  "fullDescription": "<b><br>Aktion: jetzt nur für kurze Zeit! Finanzierung mit einem effektiven Jahreszins ab 2,99%<br><br><br>Weitere Ausstattung:</b><br>3.Sitzreihe, Einzelsitze elektr. klappbar (2 Sitzplätze), Adaptive Geschwindigkeits-Regelanlage mit Stop&amp;Go-Funktion, Aktive Geräuschkompensation, Anhängerkupplung Vorbereitung, Antischlupfregelung (ASR), Audio-Navigationssystem Ford mit AppLink, Außenspiegel andersfarbig lackiert / Kontrastfarbe, Außenspiegel elektr. verstell- und heizbar, mit Memory, Brillenfach in Dachhimmel / Dachkonsole integriert, Dachreling schwarz, Einstiegschienen mit Modell-Schriftzug, Elektr. Bremskraftverteilung (EBD), Elektromotor 74 kW (Hybridantrieb), Fahrassistenz-System: aktiver Park-Assistent Plus, Ein- und Auspark-Funktion und teilautomatisierter Fahrzeugführung, Fahrassistenz-System: Ausweich-Assistent (Evasive Steer Assistance, ESA), Fahrassistenz-System: Bergabfahr-Assistent, Fahrassistenz-System: Berganfahr-Assistent (Hill-Holder), Fahrassistenz-System: Notbrems-Assistent, Fahrassistenz-System: Post-Collision-System, Fahrassistenz-System: Pre-Collision-System, Fensterheber elektrisch vorn + hinten, FordPass Connect inkl. eCall, Frontkamera mit Split View, Fußmatten Velours mit Ziernähte, Gepäckraumabdeckung / Rollo, Getriebe Automatik - Typ: 10R80 (10-Stufen), Heckleuchten LED, Heckspoiler Wagenfarbe, Induktionsladeschale für mobile Endgeräte, Innenausstattung: Carbon-Dekor, Innenspiegel mit Abblendautomatik, Intelligent Protection System (IPS), Intelligenter Geschwindigkeits-Begrenzer, Isofix-Aufnahmen für Kindersitz, Karosserie: 5-türig, Klimaautomatik 2-Zonen, Kofferraumdeckel / Heckklappe elektr. betätigt (Öffnung, sensorgesteuert), Kombiinstrument Digitalanzeige 12,3 Zoll, Lackierung Liquid-Weiß, Lenkrad (Sport/Leder, ST), Lenkrad heizbar, Lenkrad mit Schaltwippen, Lenksäule (Lenkrad) elektr. höhen-/längsverstellbar mit Memory, LM-Felgen, Motor 3,0 Ltr. - 267 kW EcoBoost Hybrid, My Key (2. Fahrzeugschlüssel programmierbar), Nebelscheinwerfer LED, Panorama-Schiebedach elektr. mit Solar-Reflect, Parkbremse elektrisch mit Auto-Hold-Funktion, Parkpilotsystem vorn und hinten, Radstand 3025 mm, Reifendruck-Kontrollsystem, Reserverad als Notrad, Rückfahrkamera mit Split View, Schadstoffarm nach Abgasnorm Euro 6d-TEMP, Scheinwerfer LED, Scheinwerfer-Assistent mit Tag-/Nachtsensor, Sitz vorn links elektr. verstellbar (10-fach, mit Memory), Sitz vorn rechts elektr. verstellbar (8-fach), Sitzausstattung: 7-Sitzer, Sitzbezug / Polsterung: Leder Premium, Sitze vorn klimatisiert, Sound-System Bang &amp; Olufsen Play, Sport-Fahrwerk, Sportsitze vorn, Start/Stop-Anlage, Steckdose (12V-Anschluß) im Koffer-/Laderaum, Steckdose 230V, Türverkleidung Leder, Verglasung hinten abgedunkelt (Privacy Glass), Wankneigungskontrolle (Roll Stability Control, RSC)<br><br>Änderungen, Inserats- bzw. Druckfehler und Zwischenverkauf vorbehalten. Inzahlungnahme Ihres gebrauchten Fahrzeuges gern möglich. Finanzierung möglich. Sie erreichen uns täglich im Zeitraum von 8.30 Uhr bis 18.00 Uhr (Samstags von 9.00 Uhr bis 12.00 Uhr). Ulf Degenhardt und Team!",
  "price": "45990",
  "currency": "EUR",
  "date": "",
  "id": 429251699,
  "imgUrls": [
    "https://img.classistatic.de/api/v1/mo-prod/images/22/22ee4195-1b64-47be-81c0-0b62c19193b1?rule=mo-1600",
    "https://img.classistatic.de/api/v1/mo-prod/images/b1/b100baff-ae7c-43f5-b6ac-4898f59f89cd?rule=mo-1600",
    "https://img.classistatic.de/api/v1/mo-prod/images/2e/2ec14b72-124f-4163-a7c7-40f1211a2e59?rule=mo-1600",
    "https://img.classistatic.de/api/v1/mo-prod/images/e0/e08bc2e3-7a31-4078-a4a9-58fe942d210d?rule=mo-1600",
    "https://img.classistatic.de/api/v1/mo-prod/images/4a/4a2e5667-8357-446a-b8aa-2dcc212a364d?rule=mo-1600",
    "https://img.classistatic.de/api/v1/mo-prod/images/1f/1f871474-5800-4195-867b-88b1cda9a5d6?rule=mo-1600",
    "https://img.classistatic.de/api/v1/mo-prod/images/9f/9f76160c-4356-4dd8-abb2-b734f097d8a3?rule=mo-1600",
    "https://img.classistatic.de/api/v1/mo-prod/images/d1/d1fdaaf0-2897-4082-bbd9-1ae7641354ef?rule=mo-1600",
    "https://img.classistatic.de/api/v1/mo-prod/images/d6/d691a4bc-4493-45df-a32c-42129c8917ee?rule=mo-1600",
    "https://img.classistatic.de/api/v1/mo-prod/images/f2/f24e66f8-3106-46ff-bac0-2ca570b82a34?rule=mo-1600",
    "https://img.classistatic.de/api/v1/mo-prod/images/14/14f75d9e-6bdf-4130-892c-219aaa29785b?rule=mo-1600",
    "https://img.classistatic.de/api/v1/mo-prod/images/2a/2a93a576-153d-4709-ac22-87904252e6bc?rule=mo-1600",
    "https://img.classistatic.de/api/v1/mo-prod/images/6a/6ac3308c-92ea-4bec-b042-b7a2bae1b4e6?rule=mo-1600",
    "https://img.classistatic.de/api/v1/mo-prod/images/b3/b30be458-e3c9-4e82-80c1-1d6e040d9eb3?rule=mo-1600",
    "https://img.classistatic.de/api/v1/mo-prod/images/9c/9c4fd357-e374-47ed-b225-c7b6cc0a1b75?rule=mo-1600",
    "https://img.classistatic.de/api/v1/mo-prod/images/4d/4da0469c-8719-4cd4-83b4-eca170eae9c5?rule=mo-1600",
    "https://img.classistatic.de/api/v1/mo-prod/images/73/736583b9-e38c-4a38-8431-e26240a50319?rule=mo-1600",
    "https://img.classistatic.de/api/v1/mo-prod/images/85/858e9924-8b56-47b0-ba13-a6da92732788?rule=mo-1600",
    "https://img.classistatic.de/api/v1/mo-prod/images/4f/4f5a139b-5b53-4ee4-a82f-39ab01beb131?rule=mo-1600",
    "https://img.classistatic.de/api/v1/mo-prod/images/c4/c4609fa7-437d-47b9-aa20-c98adf25c4cf?rule=mo-1600",
    "https://img.classistatic.de/api/v1/mo-prod/images/08/088a3dd7-89a6-49bd-9a54-5e6825ef52d1?rule=mo-1600",
    "https://img.classistatic.de/api/v1/mo-prod/images/09/091b2b06-07c7-402b-af75-a5a0915c7865?rule=mo-1600",
    "https://img.classistatic.de/api/v1/mo-prod/images/6b/6bdb8c35-e6ef-4bdf-91c4-111330826f34?rule=mo-1600",
    "https://img.classistatic.de/api/v1/mo-prod/images/45/45ccd275-42cb-4802-9413-af8c405dc4af?rule=mo-1600",
    "https://img.classistatic.de/api/v1/mo-prod/images/c7/c7f6d8ef-a316-4840-acb6-6f4c457a3fff?rule=mo-1600",
    "https://img.classistatic.de/api/v1/mo-prod/images/72/72419db3-0266-411a-a3bf-c0835b25db22?rule=mo-1600",
    "https://img.classistatic.de/api/v1/mo-prod/images/d3/d3d60a99-9ccb-4622-87e6-3e0201c3241c?rule=mo-1600",
    "https://img.classistatic.de/api/v1/mo-prod/images/e8/e81426aa-50e7-4658-a042-bf0137684578?rule=mo-1600",
    "https://img.classistatic.de/api/v1/mo-prod/images/3d/3d222020-b2b2-4202-9c74-9eaf8837cca7?rule=mo-1600"
  ]
}